{
  "codes": {
    "404": 1,
    "200": 24
  },
  "content": {
    "genre": [
      [
        5,
        "Akcja"
      ],
      [
        6,
        "Przygodowe"
      ],
      [
        7,
        "Komedia"
      ],
      [
        8,
        "Dramat"
      ],
      [
        9,
        "Sci-Fi"
      ],
      [
        12,
        "Tajemnica"
      ],
      [
        13,
        "Przygodowe"
      ],
      [
        14,
        "Komedia"
      ],
      [
        17,
        "Dramat"
      ],
      [
        18,
        "Magia"
      ],
      [
        19,
        "Nadprzyrodzone"
      ],
      [
        20,
        "Kryminalne"
      ],
      [
        22,
        "Fantasy"
      ],
      [
        24,
        "Akcja"
      ]
    ],
    "target_group": [
      [
        23,
        "Shounen"
      ]
    ],
    "entity": [],
    "setting": [
      [
        10,
        "Kosmos"
      ]
    ],
    "tag": [],
    "studio": [
      [
        1,
        "Sunrise"
      ],
      [
        2,
        "Bandai Visual"
      ],
      [
        3,
        "Funimation"
      ],
      [
        4,
        "Bandai Entertainment"
      ],
      [
        11,
        "Bones"
      ],
      [
        15,
        "Madhouse"
      ],
      [
        16,
        "Geneon Universal Entertainment"
      ],
      [
        21,
        "Toei Animation"
      ]
    ],
    "type": [],
    "publisher": [],
    "precursor": []
  }
}